{
 "ticker": "DMMX",
 "collected_date": "2026-07-14",
 "snippets": [
  {
   "source_url": "https://www.idx.co.id/en/listed-companies/company-profiles/DMMX",
   "source_type": "filing",
   "source_date": "2026-03-31",
   "text": "[1620300_BD] Notes to the financial statements - Trade receivables, by list of counterparty (breakdown) - General Industry\nRincian piutang usaha berdasarkan rincian pihak Trade receivables by list of counterparty Rincian piutang usaha berdasarkan rincian pihak Trade receivables by list of counterparty\nPiutang usaha [baris komponen] Piutang usaha [baris komponen]\nNama pihak, piutang usaha Piutang usaha, kotor Nama pihak, piutang usaha Piutang usaha, kotor\nPihak ketiga Pihak 1 PT Piranti Teknologi Unggul 36,905,729,825 Third party Rank 1, counterparty Pihak ketiga Pihak 1 Perusahaan Umum Percetakan Uang Republik Indonesia 57,730,000,000 Third party Rank 1, counterparty\nPihak 2 PT Fast Food Indonesia Tbk 28,275,956,401 Rank 2, counterparty Pihak 2 PT Piranti Teknologi Unggul 35,941,332,576 Rank 2, counterparty\nPihak 3 Rank 3, counterparty Pihak 3 PT Fast Food Indonesia Tbk 25,162,856,615 Rank 3, counterparty\nPihak 4 Rank 4, counterparty Pihak 4 Rank 4, counterparty\nPihak 5 Rank 5, counterparty Pihak 5 Rank 5, counterparty\nPihak 6 Rank 6, counterparty Pihak 6 Rank 6, counterparty\nPihak 7 Rank 7, counterparty Pihak 7 Rank 7, counterparty\nPihak 8 Rank 8, counterparty Pihak 8 Rank 8, counterparty\nPihak 9 Rank 9, counterparty Pihak 9 Rank 9, counterparty\nPihak 10 Rank 10, counterparty Pihak 10 Rank 10, counterparty\nPihak lainnya 46,230,692,328 Others, counterparty Pihak lainnya 35,428,283,108 Others, counterparty\nRincian pihak 111,412,378,554 List of counterparty Rincian pihak 154,262,472,299 List of counterparty\nPihak berelasi Pihak 1 PT Omega Kreasi Bersama 9,809,904,261 Related party Rank 1, counterparty Pihak berelasiPihak 1 PT Omega Kreasi Bersama 15,697,364,682 Related party Rank 1, counterparty\nPihak 2 PT Anugerah Wicaksana Digital 5,692,659,997 Rank 2, counterparty Pihak 2 PT Anugerah Wicaksana Digital 6,333,620,380 Rank 2, counterparty\nPihak 3 PT M Cash Integrasi Tbk 2,630,402,709 Rank 3, counterparty Pihak 3 PT M Cash Integrasi Tbk 751,298,532 Rank 3, counterparty\nPihak 4 PT Chat Bot Nusantara 258,829,629 Rank 4, counterparty Pihak 4 PT Chat Bot Nusantara 248,435,901 Rank 4, counterparty\nPihak 5 PT Jalan Terus Saja 63,492,000 Rank 5, counterparty Pihak 5 PT Energi Selalu Baru 20,300,000 Rank 5, counterparty\nPihak 6 PT Jaya Distribusi Ritel 62,306,797 Rank 6, counterparty Pihak 6 PT Inova Duapuluh Duapuluh 12,831,977 Rank 6, counterparty\nPihak 7 PT Energi Selalu Baru 20,300,000 Rank 7, counterparty Pihak 7 PT Nusantara Semesta Mandiri 9,241,838 Rank 7, counterparty\nPihak 8 PT Inova Duapuluh Duapuluh 12,831,977 Rank 8, counterparty Pihak 8 Rank 8, counterparty\nPihak 9 PT Nusantara Semesta Mandiri 9,241,838 Rank 9, counterparty Pihak 9 PT Volta Indonesia Semesta 2,997,000 Rank 9, counterparty\nPihak 10 PT Volta Indonesia Semesta 5,994,000 Rank 10, counterparty Pihak 10 Rank 10, counterparty\nPihak lainnya Others, counterparty Pihak lainnya Others, counterparty\nRincian pihak 18,565,963,208 List of counterparty Rincian pihak 23,076,090,310 List of counterparty\nRincian piutang usaha berdasarkan rincian pihak Trade receivables by list of counterparty Rincian piutang usaha berdasarkan rincian pihak Trade receivables by list of counterparty\nPiutang usaha [baris komponen] Piutang usaha [baris komponen]\nPiutang usaha, kotor Penyisihan penurunan nilai piutang usaha Piutang usaha Piutang usaha, kotor Penyisihan penurunan nilai piutang usaha Piutang usaha\nPihak ketiga Rincian pihak 111,412,378,554 ( 2,039,449,382 ) 109,372,929,172 Third partyList of counterparty Pihak ketiga Rincian pihak 154,262,472,299 ( 2,039,449,382 ) 152,223,022,917 Third partyList of counterparty\nRincian piutang usaha berdasarkan rincian pihak Trade receivables by list of counterparty Rincian piutang usaha berdasarkan rincian pihak Trade receivables by list of counterparty\nPiutang usaha [baris komponen] Piutang usaha [baris komponen]\nPiutang usaha, kotor Penyisihan penurunan nilai piutang usaha Piutang usaha Piutang usaha, kotor Penyisihan penurunan nilai piutang usaha Piutang usaha\nPihak berelasi Rincian pihak 18,565,963,208 ( 36,190,435 ) 18,529,772,773 Related partyList of counterparty Pihak berelasi Rincian pihak 23,076,090,310 ( 36,190,435 ) 23,039,899,875 Related partyList of counterparty"
  },
  {
   "source_url": "https://www.idx.co.id/en/listed-companies/company-profiles/DMMX",
   "source_type": "filing",
   "source_date": "2026-03-31",
   "text": "[1640300] Notes to the financial statements - Trade Payable, by list of counterparty - General Industry\nRincian utang usaha berdasarkan Trade payables by list of Rincian utang usaha berdasarkan Trade payables by list of\nrincian pihak counterparty rincian pihak counterparty\nUtang usaha [baris komponen] Utang usaha [baris komponen]\nNama pihak, utang usaha Utang usaha Nama pihak, utang usaha Utang usaha\nPihak Pihak 1 PT Kharisma Pesat Mandiri 842,780,702 Third Rank 1, Pihak Pihak 1 PT Kharisma Pesat Mandiri 552,496,726 Third Rank 1,\nketiga party counterparty ketiga party counterparty\nPihak 2 PT Data Proteksindo 581,083,862 Rank 2, Pihak 2 PT Galva Technologies Tbk 403,732,629 Rank 2,\ncounterparty counterparty\nPihak 3 PT Galva Technologies Tbk 275,188,114 Rank 3, Pihak 3 PT Ingram Micro Indonesia 190,921,110 Rank 3,\ncounterparty counterparty\nPihak 4 PT Synnex Metrodata 263,999,990 Rank 4, Pihak 4 PT Indosat Tbk 133,468,089 Rank 4,\nIndonesia counterparty counterparty\nPihak 5 PT Indosat Tbk 133,468,089 Rank 5, Pihak 5 Rank 5,\ncounterparty counterparty\nPihak 6 Rank 6, Pihak 6 Rank 6,\ncounterparty counterparty\nPihak 7 Rank 7, Pihak 7 Rank 7,\ncounterparty counterparty\nPihak 8 Rank 8, Pihak 8 Rank 8,\ncounterparty counterparty\nPihak 9 Rank 9, Pihak 9 Rank 9,\ncounterparty counterparty\nPihak 10 Rank 10, Pihak 10 Rank 10,\ncounterparty counterparty\nPihak 1,033,435,624 Others, Pihak 1,429,865,794 Others,\nlainnya counterparty lainnya counterparty\nRincian 3,129,956,381 List of Rincian 2,710,484,348 List of\npihak counterparty pihak counterparty\nPihak Pihak 1 PT Distribusi 46,136,308,305 Related Rank 1, Pihak Pihak 1 PT Distribusi 48,059,819,298 Related Rank 1,\nberelasi VoucherNusantara Tbk party counterparty berelasi VoucherNusantara Tbk party counterparty\nPihak 2 PT ZKDigimax Excel Noble 18,719,462,200 Rank 2, Pihak 2 PT ZKDigimax Excel Noble 18,719,462,200 Rank 2,\ncounterparty counterparty\nPihak 3 PT Sinergi Teknologi Mandir 8,487,967,836 Rank 3, Pihak 3 PT Sinergi Teknologi Mandir 6,475,960,390 Rank 3,\ncounterparty counterparty\nPihak 4 PT NFC Indonesia Tbk 2,438,192,140 Rank 4, Pihak 4 PT NFC Indonesia Tbk 2,275,959,733 Rank 4,"
  },
  {
   "source_url": "https://www.idx.co.id/en/listed-companies/company-profiles/DMMX",
   "source_type": "filing",
   "source_date": "2026-03-31",
   "text": "counterparty counterparty\nPihak 5 PT Berkah Karunia Kreasi 1,027,695,843 Rank 5, Pihak 5 PT Berkah Karunia Kreasi 1,068,812,449 Rank 5,\ncounterparty counterparty\nPihak 6 PT Abdi Anugerah Persada 36,099,348 Rank 6, Pihak 6 PT Damcorp Digital Media 76,639,978 Rank 6,\ncounterparty counterparty\nPihak 7 PT DAM Korporindo Digital 26,651,941 Rank 7, Pihak 7 PT Jaya Distribusi Ritel 65,643,532 Rank 7,\ncounterparty counterparty\nPihak 8 PT Damcorp Digital Media 23,601,971 Rank 8, Pihak 8 PT Abdi Anugerah Persada 36,730,345 Rank 8,\ncounterparty counterparty\nPihak 9 PT Berkah Trijaya Indonesia 274,265 Rank 9, Pihak 9 PT Berkah Trijaya Indonesia 75,716 Rank 9,\ncounterparty counterparty\nPihak 10 Rank 10, Pihak 10 PT Sentra Awan Maxima 392,605,002 Rank 10,\ncounterparty counterparty\nPihak Others, Pihak Others,\nlainnya counterparty lainnya counterparty\nRincian 76,896,253,849 List of Rincian 77,171,708,643 List of\npihak counterparty pihak counterparty"
  }
 ],
 "source_file": "FinancialStatement-2026-I-DMMX.pdf"
}