{
 "ticker": "TRIM",
 "collected_date": "2026-07-14",
 "snippets": [
  {
   "source_url": "https://www.idx.co.id/en/listed-companies/company-profiles/TRIM",
   "source_type": "filing",
   "source_date": "2026-03-31",
   "text": "[5220000] Statement of financial position presented using order of liquidity -\nSecurities Industry\nLaporan posisi keuangan Statement of financial position\n31 March 2026 31 December 2025\nLaporan posisi keuangan Statement of financial position\nAset Assets\nKas dan setara kas 823,312,820 779,927,087 Cash and cash equivalents\nDana yang dibatasi Restricted funds\npenggunaannya\nDeposito pada lembaga 26,881,426 21,591,495 Deposits to clearing and\nkliring dan penjaminan settlement guarantee\ninstitution\nPiutang dari lembaga 61,645,915 Receivables from clearing\nkliring dan penjaminan and settlement guarantee\ninstitution\nPiutang nasabah Receivables from\ncustomers\nPiutang nasabah 2,860,672,184 879,742,924 Receivables from\npihak ketiga customers third parties\nPiutang nasabah 105,406,860 52,718,259 Receivables from\npihak berelasi customers related parties\nPiutang perusahaan efek 1,985,500 Receivables from brokers\nPiutang margin 194,597,363 209,407,730 Margin receivables\nPiutang kegiatan manajer 66,232,329 64,999,228 Receivables from\ninvestasi investment manager\nPiutang kegiatan 36,965,433 9,896,358 Receivables from\npenjaminan emisi efek underwriting and advisory\ndan jasa penasehat services\nPiutang lainnya 8,640,910 9,483,370 Other receivables\nEfek yang 619,701,644 426,794,879 Marketable securities\ndiperdagangkan\nEfek yang dibeli dengan 3,956,465,870 4,171,361,328 Securities purchased under\njanji dijual kembali agreement to resale\nAset keuangan derivatif Derivative financial assets\nPendapatan yang masih Accrued income\nharus diterima\nPajak dibayar dimuka Prepaid taxes\nBiaya dibayar dimuka 24,044,312 28,148,292 Prepaid expenses\nJaminan Guarantees\nUang muka 2,326,921 2,019,425 Advances\nPenyertaan pada bursa 10,500,000 10,500,000 Investments in shares of\nefek Indonesia indonesia stock exchange\nKlaim atas pengembalian Claims for tax refund\npajak\nInvestasi yang dicatat Investments accounted for\ndengan menggunakan using equity method\nmetode ekuitas\nInvestasi pada ventura Investments in joint\nbersama dan entitas ventures and associates\nasosiasi\nInvestasi pada entitas Investments in joint\nventura bersama ventures\nInvestasi pada entitas Investments in\nasosiasi associates\nAset pajak tangguhan 42,657,793 44,387,348 Deferred tax assets"
  },
  {
   "source_url": "https://www.idx.co.id/en/listed-companies/company-profiles/TRIM",
   "source_type": "filing",
   "source_date": "2026-03-31",
   "text": "Aset imbalan pasca kerja Post-employment benefit\nassets\nGoodwill Goodwill\nAset takberwujud selain 9,948,254 11,396,044 Intangible assets other than\ngoodwill goodwill\nProperti investasi Investment properties\nAset pengampunan pajak Tax amnesty assets\nAset tetap 48,243,508 38,095,094 Property, plant, and\nequipment\nAset hak guna Right of use assets\nAset lainnya 8,281,865 3,944,948 Other assets\nJumlah aset 8,844,879,492 6,828,045,224 Total assets\nLiabilitas dan ekuitas Liabilities and equity\nLiabilitas Liabilities\nWesel bayar Notes payable\nSurat utang jangka Medium term notes\nmenengah\nUtang obligasi 2,355,886,125 2,356,754,342 Bonds payable\nSukuk Sukuk\nObligasi subordinasi Subordinated bonds\nUtang bank 1,040,000,000 1,250,000,000 Bank loans\nUtang lembaga Non-bank financial\nkeuangan non-bank insitutions loan\nUtang kepada 185,239,211 62,308,828 Payables to clearing and\nlembaga kliring dan settlement guarantee\npenjaminan institution\nUtang nasabah Payables to customers\nUtang nasabah 2,681,066,285 689,657,382 Payables to\npihak ketiga customers third\nparties\nUtang nasabah 3,386 9,022,253 Payables to\npihak berelasi customers related\nparties\nUtang kegiatan Payables to investment\nmanajer investasi managers\nUtang perusahaan Payables to securities\nefek company\nUtang dividen Dividends payable\nUtang marjin 9,308,256 18,386,905 Margin payables\nBeban akrual 182,717,415 199,520,196 Accrued expenses\nUtang pajak 50,748,366 38,907,351 Taxes payable\nLiabilitas pajak Deferred tax liabilities\ntangguhan\nLiabilitas atas kontrak Contract liabilities\nUtang pihak berelasi Due to related parties\nPinjaman subordinasi Subordinated loans\nKewajiban imbalan 50,928,478 49,008,475 Post-employment benefit\npasca kerja obligations\nLiabilitas Tax amnesty liabilities\npengampunan pajak\nLiabilitas lainnya 57,139,733 79,653,651 Other liabilities\nJumlah liabilitas 6,613,037,255 4,753,219,383 Total liabilities\nEkuitas Equity\nEkuitas yang Equity attributable to\ndiatribusikan kepada equity owners of\npemilik entitas induk parent entity\nSaham biasa 355,465,000 355,465,000 Common stocks"
  },
  {
   "source_url": "https://www.idx.co.id/en/listed-companies/company-profiles/TRIM",
   "source_type": "filing",
   "source_date": "2026-03-31",
   "text": "dan ditentukan sebagai suatu aset individual, kecuali aset tersebut tidak menghasilkan arus kas masuk\nyang sebagian besar independen dari aset lain.Di dalam menilai nilai pakai, estimasi arus kas yang\ndiharapkan diperoleh dari aset didiskontokan terhadap nilai kininya dengan menggunakan suku bunga\ndiskon sebelum pajak yang mencerminkan penilaian pasar kini terhadap nilai waktu uang dan risiko\nspesifik aset. Di dalam menilai nilai wajar dikurangi biaya untuk menjual, dibutuhkan model penilaian\nyang tepat.Ketika nilai tercatat aset melebihi nilai terpulihkannya, maka aset tersebut dicatat sebesar\nnilai terpulihkan. Kerugian penurunan nilai diakui di dalam laporan laba rugi kecuali aset yang relevan\ndinilai pada jumlah yang direvaluasi, yang dalam hal ini kerugian penurunan nilai diperlakukan sebagai\npenurunan revaluasi.Suatu penilaian dilakukan pada setiap tanggal pelaporan apabila terdapat segala\nindikasi bahwa kerugian penurunan nilai yang diakui sebelumnya sudah tidak ada lagi atau mengalami\npenurunan. Suatu kerugian penurunan nilai yang diakui sebelumnya, dipulihkan nilainya jika terdapat\nperubahan estimasi yang digunakan untuk menentukan nilai terpulihkan aset sejak pengakuan terakhir\nkerugian penurunan nilai. Apabila demikian kondisinya, nilai tercatat aset meningkat pada jumlah\nterpulihkannya. Kenaikan tersebut tidak dapat melebihi nilai tercatat yang telah ditentukan, setelah\ndikurangi penyusutan, tidak ada kerugian penurunan nilai yang diakui sebelumnya. Pemulihan nilai\ntersebut diakui di dalam laporan laba rugi kecuali aset tersebut diukur pada jumlah revaluasian, yang\ndalam hal ini diperlakukan sebagai kenaikan revaluasi.\nBeban tangguhan Deferred charges\nUtang usaha dan liabilitas lain-lain Trade payables and other liabilities\nPengakuan pendapatan dan beban Pendapatan komisi dari transaksi perantara perdagangan efek diakui pada saat transaksi terjadi. Revenue and expense recognition\nImbalan jasa penjaminan emisi dan penjualan efek diakui pada saat aktivitas penjaminan emisi selesai.\nImbalan jasa manajer/penasihat investasi diakui pada saat jasa tersebut sudah dilakukan dan\npendapatannya sudah ditentukan.Pendapatan provisi dan komisi termasuk biaya broker, biaya\nmanajemen investasi dan komisi penjualan diakui sebagai jasa yang telah dilakukan. Biaya lain dan\nbeban komisi sebagian besar berkaitan dengan biaya transaksi dan pelayanan yang dibebankan saat\njasa diterima. Laba rugi atas perdagangan efek diakui pada saat tanggal transaksi, dan pendapatan\nbunga diakui berdasarkan metode akrual. Penghasilan dan beban bunga dari nasabah diakui pada\nsaat terjadinya. Pendapatan dividen dari portofolio efek diakui pada saat emiten mengumumkan\npembayaran dividen. Beban diakui pada saat terjadinya (accrual basis).\nPenjabaran mata uang asing Transaksi dalam mata uang asing dijabarkan ke mata uang Rupiah dengan menggunakan kurs yang Foreign currency translation\nberlaku pada tanggal transaksi. Pada tanggal laporan posisi keuangan, aset dan liabilitas moneter\ndalam mata uang asing dijabarkan dengan kurs yang berlaku saat itu.Keuntungan dan kerugian selisih\nkurs yang timbul dari transaksi dalam mata uang asing dan penjabaran aset dan liabilitas moneter\ndalam mata uang asing, diakui pada laporan laba rugi dan penghasilan komprehensif lain\nkonsolidasian.\nTransaksi dengan pihak berelasi Transaksi antara Perusahaan dan entitas anak yang merupakan pihak berelasi, telah dieliminasi dalam Transactions with related parties\nkonsolidasian dan tidak disajikan dalam catatan ini.Perusahaan dan entitas anak dalam kegiatan\nusaha normalnya, melakukan beberapa transaksi dengan pihak berelasi tersebut diatas berdasarkan\nketentuan dan kondisi yang disepakati bersama.\nPajak penghasilan Grup memiliki eksposur atas pajak penghasilan. Pertimbangan signifikan dilakukan di dalam Income taxes\nmenentukan provisi atas pajak penghasilan. Ada beberapa transaksi dan komputasi di mana\npenentuan akhir perpajakan adalah tidak pasti di dalam kegiatan usaha normal. Grup mengakui\nliabilitias atas isu pajak yang diharapkan berdasarkan estimasi apakah penambahan pajak akan jatuh\ntempo. Pada saat hasil final perpajakan berbeda dari jumlah yang sebelumnya diakui, maka selisih\ntersebut akan berdampak pada pajak penghasilan kini dan provisi pajak tangguhan di dalam periode\ndimana penentuan tersebut dibuat."
  }
 ],
 "source_file": "FinancialStatement-2026-I-TRIM.pdf"
}