{
 "ticker": "WTON",
 "collected_date": "2026-07-14",
 "snippets": [
  {
   "source_url": "https://www.idx.co.id/en/listed-companies/company-profiles/WTON",
   "source_type": "filing",
   "source_date": "2026-03-31",
   "text": "[1616000_BD] Notes to the financial statements - Revenue By Parties (breakdown) - General Industry\n31 March 2026 31 March 2025\nCatatan untuk pendapatan berdasarkan pihak Notes for Catatan untuk pendapatan berdasarkan pihak Notes for\nrevenue by revenue by\nparties parties\nPenjualan dan Penjualan dan\nNama pihak Nama pihak\npendapatan usaha pendapatan usaha\nParty name Sales and revenue Party name Sales and revenue\nPihak PT Perusahaan Listrik Negara (Persero) 41,927,094,670 Related Pihak PT Perusahaan Listrik Negara (Persero) 69,173,280,010 Related\nberelasi 1 party 1 berelasi 1 party 1\nPihak JV Kumagai Gumi Co. Ltd - PT Wijaya Karya (Persero) - PT 28,361,926,000 Related Pihak PT Hutama Karya Infrastruktur 46,855,683,000 Related\nberelasi 2 Jaya Konstruksi Manggala Pratama Tbk party 2 berelasi 2 party 2\nPihak PT Wijaya Karya (Persero) Tbk 16,904,703,202 Related Pihak PT Bank Mandiri (Persero) Tbk 8,882,070,269 Related\nberelasi 3 party 3 berelasi 3 party 3\nPihak KSO PT Hutama Karya (Persero) - PT Wijaya Karya (Persero) 16,672,197,000 Related Pihak PT Bank Negara Indonesia (Persero) Tbk 6,636,079,087 Related\nberelasi 4 Tbk - PT Brantas Abipraya (Persero) party 4 berelasi 4 party 4\nPihak PT Hutama Karya Infrastruktur 13,855,030,286 Related Pihak PT Wijaya Karya (Persero) Tbk 4,176,546,500 Related\nberelasi 5 party 5 berelasi 5 party 5\nPihak PT Pembangunan Perumahan (Persero) Tbk 11,350,002,680 Related Pihak Related\nberelasi 6 party 6 berelasi 6 party 6\nPihak PT Wijaya Karya Rekayasa Konstruksi 8,637,492,200 Related Pihak Related\nberelasi 7 party 7 berelasi 7 party 7\nPihak PT Bank Mandiri (Persero) Tbk 3,672,117,344 Related Pihak Related\nberelasi 8 party 8 berelasi 8 party 8\nPihak PT Bank Negara Indonesia (Persero) Tbk 427,270,540 Related Pihak Related\nberelasi 9 party 9 berelasi 9 party 9\nPihak Related Pihak Related\nberelasi party berelasi party\n10 10 10 10\nPihak Lain-lain 95,895,825,568 Other Pihak Lain-lain 168,516,337,338 Other\nberelasi related berelasi related\nlainnya parties lainnya parties\nPihak 237,703,659,490 Related Pihak 304,239,996,204 Related\nberelasi parties berelasi parties\nPihak KSO PT Pembangunan Perumahan (Persero) Tbk - PT Adhi 39,092,906,570 Third Pihak KSO PT Pembangunan Perumahan (Persero) Tbk - PT Adhi 35,707,997,665 Third\nketiga 1 Karya (Persero) Tbk - PT Waskita Karya (Persero) Tbk - PT party 1 ketiga 1 Karya (Persero) Tbk - PT Waskita Karya (Persero) Tbk - PT party 1"
  },
  {
   "source_url": "https://www.idx.co.id/en/listed-companies/company-profiles/WTON",
   "source_type": "filing",
   "source_date": "2026-03-31",
   "text": "Modern Wijaya Tehnical Modern Wijaya Tehnical\nPihak PT Jakarta Propertindo 27,845,123,286 Third Pihak PT Lancang Kuning Sukses 25,906,236,000 Third\nketiga 2 party 2 ketiga 2 party 2\nPihak PT OKI Pulp Paper Mills 23,711,344,468 Third Pihak PT Freeport Indonesia 13,156,216,320 Third\nketiga 3 party 3 ketiga 3 party 3\nPihak PT Sumber Urip Sejati 19,766,980,790 Third Pihak PT Fajar Putra Dinasti 10,945,499,531 Third\nketiga 4 party 4 ketiga 4 party 4\nPihak PT Riya Pasifik Nabati 18,324,403,500 Third Pihak PT Jakarta Propertindo 5,399,758,831 Third\nketiga 5 party 5 ketiga 5 party 5\nPihak PT Makassar International Expo 18,213,648,000 Third Pihak PT Mulia Boga Raya Tbk 5,262,484,607 Third\nketiga 6 party 6 ketiga 6 party 6\nPihak PT Larsen Toubro Limited 17,402,944,653 Third Pihak PT Girder Indonesia 5,007,800,000 Third\nketiga 7 party 7 ketiga 7 party 7\nPihak PT Indah Kiat Pulp Paper Tbk. 16,285,043,755 Third Pihak Third\nketiga 8 party 8 ketiga 8 party 8\nPihak PT Fajar Putra Dinasti 15,694,317,410 Third Pihak Third\nketiga 9 party 9 ketiga 9 party 9\nPihak KSO PT Hutama Karya (Persero) - PT Brantas Abipraya 10,709,860,000 Third Pihak Third\nketiga 10 (Persero) - PT Jaya Konstruksi Manggala Pratama Tbk - PT party ketiga 10 party\nYasa Patria Perkasa 10 10\nPihak Lain-lain 232,287,167,606 Other Pihak 465,973,470,508 Other\nketiga third ketiga third\nlainnya parties lainnya parties\nPihak 439,333,740,038 Third Pihak 567,359,463,462 Third\nketiga parties ketiga parties\nTipe 677,037,399,528 Type of Tipe 871,599,459,666 Type of\npihak parties pihak parties"
  },
  {
   "source_url": "https://www.idx.co.id/en/listed-companies/company-profiles/WTON",
   "source_type": "filing",
   "source_date": "2026-03-31",
   "text": "[1620300_BD] Notes to the financial statements - Trade receivables, by list of counterparty (breakdown) - General Industry\nRincian piutang usaha berdasarkan rincian pihak Trade receivables by list of Rincian piutang usaha berdasarkan rincian pihak Trade receivables by list of\ncounterparty counterparty\nPiutang usaha [baris komponen] Piutang usaha [baris komponen]\nPiutang usaha, Piutang usaha,\nNama pihak, piutang usaha Nama pihak, piutang usaha\nkotor kotor\nPihak Pihak 1 KSO PT Pembangunan Perumahan (Persero) Tbk - PT Adhi Karya (Persero) Tbk - PT Waskita Karya (Persero) 31,680,973,721 Third Rank 1, Pihak Pihak 1 KSO PT Pembangunan Perumahan (Persero) Tbk - PT Adhi Karya (Persero) Tbk - PT Waskita Karya 29,734,120,104 Third Rank 1,\nketiga Tbk - PT Modern Wijaya Tehnical party counterparty ketiga (Persero) Tbk - PT Modern Wijaya Tehnical party counterparty\nPihak 2 PT Girder Indonesia 31,517,698,725 Rank 2, Pihak 2 KSO PT Adhi Karya (Persero) Tbk - PT Brantas Abipraya (Persero) -PT Marga Konstruksi Nusantara 27,169,563,958 Rank 2,\ncounterparty counterparty\nPihak 3 PT Truba Jaya Engineering 29,734,120,104 Rank 3, Pihak 3 KSO PT Brantas Abipraya (Persero) - PT Guntur Satria Perkasa 25,484,674,200 Rank 3,\ncounterparty counterparty\nPihak 4 PT Jaya Bersama Alexindo 19,437,719,600 Rank 4, Pihak 4 KSO PT Hutama Karya (Persero) - PT Brantas Abipraya (Persero) -PT Jaya Konstruksi Manggala 23,229,219,350 Rank 4,\ncounterparty Pratama Tbk - PT Yasa Patria Perkasa counterparty\nPihak 5 KSO PT Adhi Karya (Persero) Tbk - PT Brantas Abipraya (Persero) - PT Marga Konstruksi Nusantara 19,245,669,100 Rank 5, Pihak 5 PT Truba Jaya Engineering 17,932,629,610 Rank 5,\ncounterparty counterparty\nPihak 6 PT Fajar Putra Dinasti 18,628,640,766 Rank 6, Pihak 6 KSO PT Hutama Karya Infrastruktur - PT Acset Indonusa Tbk -PT Nindya Karya 16,531,091,549 Rank 6,\ncounterparty counterparty\nPihak 7 PT Indah Kiat Pulp Paper Tbk 16,298,668,237 Rank 7, Pihak 7 PT Rekagunatek Persada 15,737,670,000 Rank 7,\ncounterparty counterparty\nPihak 8 KSO PT Hutama Karya (Persero) - PT Brantas Abipraya (Persero) 15,416,435,960 Rank 8, Pihak 8 PT Nusa Raya Cipta Tbk 10,204,689,478 Rank 8,\ncounterparty counterparty\nPihak 9 PT Sumber Urip Sejati 13,848,858,479 Rank 9, Pihak 9 PT Jaya Bersama Alexindo 10,181,580,300 Rank 9,\ncounterparty counterparty\nPihak 10 KSO PT Hutama Karya Infrastruktur - PT Acset Indonusa Tbk. - PT Nindya Karya 10,613,917,500 Rank 10, Pihak 10 PT Karya Logistik Nusantara 9,357,301,133 Rank 10,\ncounterparty counterparty\nPihak Lain-lain 296,511,762,769 Others, Pihak Lain-lain 283,370,594,437 Others,\nlainnya counterparty lainnya counterparty\nRincian 502,934,464,961 List of Rincian 468,933,134,119 List of\npihak counterparty pihak counterparty\nPihak Pihak 1 PT Wijaya Karya (Persero) Tbk 235,692,237,357 Related Rank 1, Pihak Pihak 1 KSO PT Adhi Karya (Persero) Tbk - PT Brantas Abipraya (Persero) - PT Marga Konstruksi Nusantara 207,480,336,071 Related Rank 1,\nberelasi party counterparty berelasi party counterparty\nPihak 2 PT Adhi Karya (Persero) Tbk 23,676,188,850 Rank 2, Pihak 2 PT Truba Jaya Engineering 26,476,837,021 Rank 2,\ncounterparty counterparty\nPihak 3 PT Pembangunan Perumahan (Persero) Tbk 21,683,329,913 Rank 3, Pihak 3 PT Indah Kiat Pulp Paper Tbk 23,733,669,370 Rank 3,\ncounterparty counterparty\nPihak 4 PT Hutama Karya Infrastruktur 17,235,613,100 Rank 4, Pihak 4 KSO PT Brantas Abipraya (Persero) - PT Guntur Satria Perkasa 22,940,285,362 Rank 4,\ncounterparty counterparty\nPihak 5 PT Wijaya Karya Bangunan Gedung Tbk 16,290,486,210 Rank 5, Pihak 5 KSO PT Hutama Karya (Persero) - PT Brantas Abipraya (Persero) - PT Jaya Konstruksi Manggala 18,945,765,061 Rank 5,\ncounterparty Pratama Tbk - PT Yasa Patria Perkasa counterparty\nPihak 6 KSO China Road Bridge Corporation - PT Wijaya Karya (Persero) Tbk - PT Pembangunan Perumahan (Persero) 10,492,543,165 Rank 6, Pihak 6 PT Rekagunatek Persada 18,251,905,750 Rank 6,\nTbk counterparty counterparty\nPihak 7 PT Wijaya Karya Rekayasa Konstruksi 8,516,676,549 Rank 7, Pihak 7 KSO PT Hutama Karya Infrastruktur - PT Acset Indonusa Tbk. - PT Nindya Karya 14,213,763,438 Rank 7,\ncounterparty counterparty\nPihak 8 PT Waskita Beton Precast Tbk 1,400,367,252 Rank 8, Pihak 8 PT Jakarta Propertindo 3,432,723,846 Rank 8,\ncounterparty counterparty\nPihak 9 High Speed Railway Contractor Consortium (HSRCC) - Team WIKA 313,125,688 Rank 9, Pihak 9 PT Dian Previta 2,928,347,200 Rank 9,\ncounterparty counterparty"
  }
 ],
 "source_file": "FinancialStatement-2026-I-WTON.pdf"
}